georeverse.py
setup.py
Georeverse.egg-info/PKG-INFO
Georeverse.egg-info/SOURCES.txt
Georeverse.egg-info/dependency_links.txt
Georeverse.egg-info/top_level.txt